django_managerie/__init__.py
django_managerie/blocklist.py
django_managerie/commands.py
django_managerie/forms.py
django_managerie/managerie.py
django_managerie/py.typed
django_managerie/types.py
django_managerie/views.py
django_managerie/templates/django_managerie/admin/command.html
django_managerie/templates/django_managerie/admin/list.html
django_managerie-0.6.1.dist-info/METADATA
django_managerie-0.6.1.dist-info/WHEEL
django_managerie-0.6.1.dist-info/licenses/LICENSE
django_managerie-0.6.1.dist-info/RECORD
