Metadata-Version: 2.4
Name: django-managerie
Version: 0.6.1
Summary: Expose Django management commands in the admin
Project-URL: Homepage, https://github.com/akx/django-managerie
Author-email: Aarni Koskela <akx@iki.fi>
License-Expression: MIT
License-File: LICENSE
Classifier: Intended Audience :: Developers
Classifier: License :: OSI Approved :: MIT License
Classifier: Programming Language :: Python :: 3
Classifier: Programming Language :: Python :: 3 :: Only
Classifier: Programming Language :: Python :: 3.10
Classifier: Programming Language :: Python :: 3.11
Classifier: Programming Language :: Python :: 3.12
Classifier: Programming Language :: Python :: 3.13
Requires-Python: >=3.10
Requires-Dist: django>=4.2
Provides-Extra: dev
Requires-Dist: pytest-django~=4.10; extra == 'dev'
Requires-Dist: pytest>=7.2; extra == 'dev'
